flake8_builtins-stubs/METADATA.toml
flake8_builtins-stubs/__init__.pyi
flake8_builtins-stubs/py.typed
types_flake8_builtins-3.0.0.20250819.dist-info/licenses/LICENSE
types_flake8_builtins-3.0.0.20250819.dist-info/METADATA
types_flake8_builtins-3.0.0.20250819.dist-info/WHEEL
types_flake8_builtins-3.0.0.20250819.dist-info/top_level.txt
types_flake8_builtins-3.0.0.20250819.dist-info/RECORD
